{"type": "Feature", "id": 12517750, "geometry": {"type": "Point", "coordinates": [98.968483, 18.76775]}, "properties": {"woe:id": 12517750, "woe:parent_id": 55947126, "woe:name": "Chiang Mai International Airport", "woe:placetype": 14, "woe:placetype_name": "Airport", "woe:lang": "ENG", "iso:country": "TH", "meta:provider": ["geoplanet:7.3.1", "geoplanet:7.3.2", "geoplanet:7.4.0", "geoplanet:7.4.1", "geoplanet:7.5.1", "geoplanet:7.5.2", "geoplanet:7.6.0", "geoplanet:7.8.1", "geoplanet:7.9.0", "geoplanet:7.10.0", "geoplanet:8.0.0", "woeplanet:8.0.0"], "meta:indexed": "2020-08-20T20:27:30.706874", "woe:alias_ENG_V": ["CNX Airport", "CNX", "Chiang Mai Airport", "Chiang Mai International"], "meta:updated": "2020-10-14T11:19:25.471115", "woe:hierarchy": {"continent": 24865671, "country": 23424960, "town": 0, "planet": 1, "county": 28340822, "suburb": 0, "state": 2347129, "region": 0, "localadmin": 0}, "woe:timezone_id": 28350814, "woe:hash": "w5q6u0ddhf1t", "woe:centroid": [98.968483, 18.76775], "geom:latitude": 18.76775, "geom:longitude": 98.968483, "geom:hash": "w5q6u0ddhf1t", "woe:latitude": 18.76775, "geom:centroid": [98.968483, 18.76775], "woe:longitude": 98.968483, "woe:repo": "woeplanet-airport-th", "geom:area": 0.0, "woe:scale": 19}}