{"type": "Feature", "id": 12517792, "properties": {"woe:id": 12517792, "woe:parent_id": 55944765, "woe:name": "Udon Airport", "woe:placetype": 14, "woe:placetype_name": "Airport", "woe:lang": "ENG", "iso:country": "TH", "meta:provider": ["geoplanet:7.3.1", "geoplanet:7.3.2", "geoplanet:7.4.0", "geoplanet:7.4.1", "geoplanet:7.5.1", "geoplanet:7.5.2", "geoplanet:7.6.0", "geoplanet:7.8.1", "geoplanet:7.9.0", "geoplanet:7.10.0", "geoplanet:8.0.0", "woeplanet:8.0.0"], "meta:indexed": "2020-08-20T20:27:30.720046", "woe:alias_ENG_V": ["Udon Thani Internacional Airport", "UTH Airport", "UTH"], "meta:updated": "2020-08-22T01:58:45.950459", "woe:hierarchy": {"continent": 24865671, "country": 23424960, "town": 0, "planet": 1, "county": 28341024, "suburb": 0, "state": 2347200, "region": 0, "localadmin": 0}, "woe:timezone_id": 28350814, "woe:hash": "w714ftenb270", "woe:centroid": [102.770248, 17.389771], "geom:latitude": 17.389771, "geom:longitude": 102.770248, "geom:hash": "w714ftenb270", "woe:latitude": 17.389771, "geom:centroid": [102.770248, 17.389771], "woe:longitude": 102.770248, "woe:repo": "woeplanet-airport-th"}, "geometry": {"coordinates": [102.770248, 17.389771], "type": "Point"}}