{"type": "Feature", "id": 12517769, "properties": {"woe:id": 12517769, "woe:parent_id": 55947951, "woe:name": "Nam Phong Airport", "woe:placetype": 14, "woe:placetype_name": "Airport", "woe:lang": "ENG", "iso:country": "TH", "meta:provider": ["geoplanet:7.3.1", "geoplanet:7.3.2", "geoplanet:7.4.0", "geoplanet:7.4.1", "geoplanet:7.5.1", "geoplanet:7.5.2", "geoplanet:7.6.0", "geoplanet:7.8.1", "geoplanet:7.9.0", "geoplanet:7.10.0", "geoplanet:8.0.0", "woeplanet:8.0.0"], "meta:indexed": "2020-08-20T20:27:30.686244", "meta:updated": "2020-08-22T01:58:45.931008", "woe:hierarchy": {"continent": 24865671, "country": 23424960, "town": 0, "planet": 1, "county": 28341114, "suburb": 0, "state": 2347147, "region": 0, "localadmin": 0}, "woe:timezone_id": 28350814, "woe:hash": "w6cnxnv4cedy", "woe:centroid": [102.970802, 16.648899], "geom:latitude": 16.648899, "geom:longitude": 102.970802, "geom:hash": "w6cnxnv4cedy", "woe:latitude": 16.648899, "geom:centroid": [102.970802, 16.648899], "woe:longitude": 102.970802, "woe:repo": "woeplanet-airport-th"}, "geometry": {"coordinates": [102.970802, 16.648899], "type": "Point"}}