{"type": "Feature", "id": 56049649, "geometry": {"type": "Point", "coordinates": [101.123192, 13.29941]}, "properties": {"woe:id": 56049649, "woe:parent_id": 1201567, "woe:name": "Ban Bueng Airport", "woe:placetype": 14, "woe:placetype_name": "Airport", "woe:lang": "ENG", "iso:country": "TH", "meta:provider": ["geoplanet:7.3.1", "geoplanet:7.3.2", "geoplanet:7.4.0", "geoplanet:7.4.1", "geoplanet:7.5.1", "geoplanet:7.5.2", "geoplanet:7.6.0", "geoplanet:7.8.1", "geoplanet:7.9.0", "geoplanet:7.10.0", "geoplanet:8.0.0", "woeplanet:8.0.0"], "meta:indexed": "2020-08-20T20:27:30.701435", "meta:updated": "2020-10-14T11:19:25.445143", "woe:hierarchy": {"continent": 24865671, "country": 23424960, "town": 0, "planet": 1, "county": 28341352, "suburb": 0, "state": 2347170, "region": 0, "localadmin": 0}, "woe:timezone_id": 28350814, "woe:hash": "w4rgtj5dtjtn", "woe:centroid": [101.123192, 13.29941], "geom:latitude": 13.29941, "geom:longitude": 101.123192, "geom:hash": "w4rgtj5dtjtn", "woe:latitude": 13.29941, "geom:centroid": [101.123192, 13.29941], "woe:longitude": 101.123192, "woe:repo": "woeplanet-airport-th", "geom:area": 0.0, "woe:scale": 19}}