{"type": "Feature", "id": 12517786, "geometry": {"type": "Point", "coordinates": [99.153999, 9.13487]}, "properties": {"woe:id": 12517786, "woe:parent_id": 1222308, "woe:name": "Surat Thani Airport", "woe:placetype": 14, "woe:placetype_name": "Airport", "woe:lang": "ENG", "iso:country": "TH", "meta:provider": ["geoplanet:7.3.1", "geoplanet:7.3.2", "geoplanet:7.4.0", "geoplanet:7.4.1", "geoplanet:7.5.1", "geoplanet:7.5.2", "geoplanet:7.6.0", "geoplanet:7.8.1", "geoplanet:7.9.0", "geoplanet:7.10.0", "geoplanet:8.0.0", "woeplanet:8.0.0"], "meta:indexed": "2020-08-20T20:27:30.717642", "woe:alias_ENG_V": ["URT Airport", "URT"], "meta:updated": "2020-10-14T11:19:25.453129", "woe:hierarchy": {"continent": 24865671, "country": 23424960, "town": 0, "planet": 1, "county": 28341597, "suburb": 0, "state": 2347184, "region": 0, "localadmin": 0}, "woe:timezone_id": 28350814, "woe:hash": "w1webqcwrxhq", "woe:centroid": [99.153999, 9.13487], "geom:latitude": 9.13487, "geom:longitude": 99.153999, "geom:hash": "w1webqcwrxhq", "woe:latitude": 9.13487, "geom:centroid": [99.153999, 9.13487], "woe:longitude": 99.153999, "woe:repo": "woeplanet-airport-th", "geom:area": 0.0, "woe:scale": 19}}