{"type": "Feature", "id": 12517777, "properties": {"woe:id": 12517777, "woe:parent_id": 1219706, "woe:name": "Phuket International Airport", "woe:placetype": 14, "woe:placetype_name": "Airport", "woe:lang": "ENG", "iso:country": "TH", "meta:provider": ["geoplanet:7.3.1", "geoplanet:7.3.2", "geoplanet:7.4.0", "geoplanet:7.4.1", "geoplanet:7.5.1", "geoplanet:7.5.2", "geoplanet:7.6.0", "geoplanet:7.8.1", "geoplanet:7.9.0", "geoplanet:7.10.0", "geoplanet:8.0.0", "woeplanet:8.0.0"], "meta:indexed": "2020-08-20T20:27:30.714618", "woe:alias_ENG_V": ["Phuket International", "HKT", "HKT Airport", "Phuket Airport"], "meta:updated": "2020-08-22T01:58:45.947039", "woe:hierarchy": {"continent": 24865671, "country": 23424960, "town": 0, "planet": 1, "county": 28341616, "suburb": 0, "state": 2347186, "region": 0, "localadmin": 0}, "woe:timezone_id": 28350814, "woe:hash": "w1myj59nvr42", "woe:centroid": [98.307266, 8.10636], "geom:latitude": 8.10636, "geom:longitude": 98.307266, "geom:hash": "w1myj59nvr42", "woe:latitude": 8.10636, "geom:centroid": [98.307266, 8.10636], "woe:longitude": 98.307266, "woe:repo": "woeplanet-airport-th"}, "geometry": {"coordinates": [98.307266, 8.10636], "type": "Point"}}